Metadata-Version: 1.0
Name: c4-achitecture
Version: 0.1.dev0
Summary: UNKNOWN
Home-page: https://github.com/jieyinybl/c4-architecture.git
Author: JieyingYan
Author-email: UNKNOWN
License: MIT
Platform: UNKNOWN
